autograder_cli/__init__.py
autograder_cli/__main__.py
autograder_cli/http_client.py
autograder_cli/utils.py
autograder_cli/config/__init__.py
autograder_cli/config/init_project.py
autograder_cli/config/load_project.py
autograder_cli/config/models.py
autograder_cli/config/save_project.py
autograder_cli/config/time_processing.py
autograder_cli/config/utils.py
autograder_cli/config/autograder_io_schema/__init__.py
autograder_cli/config/autograder_io_schema/schema.py
autograder_cli/config/autograder_io_schema/schema.yml
autograder_cli-2024.8.1.dist-info/licenses/LICENSE
autograder_cli-2024.8.1.dist-info/METADATA
autograder_cli-2024.8.1.dist-info/WHEEL
autograder_cli-2024.8.1.dist-info/entry_points.txt
autograder_cli-2024.8.1.dist-info/top_level.txt
autograder_cli-2024.8.1.dist-info/RECORD
