Metadata-Version: 2.4
Name: autograder-cli
Version: 2024.8.1
Summary: A command-line http client and other utilities for using the autograder.io API.
Author-email: James Perretta <jameslp@umich.edu>
Project-URL: Homepage, https://github.com/eecs-autograder/autograder-cli
Project-URL: Issues, https://github.com/eecs-autograder/autograder-cli/issues
Keywords: autograder,autograder.io
Classifier: Programming Language :: Python :: 3
Classifier: License :: OSI Approved :: GNU Lesser General Public License v3 (LGPLv3)
Requires-Python: >=3.10
License-File: LICENSE
Requires-Dist: requests
Requires-Dist: pydantic
Requires-Dist: pydantic[email]
Requires-Dist: PyYAML
Requires-Dist: typing_extensions
Requires-Dist: python-dateutil
Requires-Dist: tzlocal
Dynamic: license-file
